python_docker_mcp/Dockerfile
python_docker_mcp/__init__.py
python_docker_mcp/__main__.py
python_docker_mcp/build_docker_image.py
python_docker_mcp/config.py
python_docker_mcp/default_config.yaml
python_docker_mcp/docker_manager.py
python_docker_mcp/server.py
python_docker_mcp-0.2.5.dist-info/METADATA
python_docker_mcp-0.2.5.dist-info/WHEEL
python_docker_mcp-0.2.5.dist-info/entry_points.txt
python_docker_mcp-0.2.5.dist-info/licenses/LICENSE
python_docker_mcp-0.2.5.dist-info/RECORD
