Metadata-Version: 2.4
Name: python-docker-mcp
Version: 0.2.5
Summary: Dockerised Python execution environment for AI agents
Project-URL: Homepage, https://github.com/artivus/python-docker-mcp
Project-URL: Bug Tracker, https://github.com/artivus/python-docker-mcp/issues
Author-email: Shannon Sands <shannon.sands.1979@gmail.com>
License: MIT
License-File: LICENSE
Keywords: agent,docker,execution,mcp,python,sandbox
Classifier: Development Status :: 4 - Beta
Classifier: Intended Audience :: Developers
Classifier: License :: OSI Approved :: MIT License
Classifier: Programming Language :: Python :: 3
Classifier: Programming Language :: Python :: 3.11
Classifier: Programming Language :: Python :: 3.12
Classifier: Topic :: Software Development :: Libraries :: Python Modules
Classifier: Topic :: Software Development :: Testing
Requires-Python: >=3.11
Requires-Dist: docker>=7.1.0
Requires-Dist: mcp>=1.5.0
Requires-Dist: pyyaml>=6.0.2
Requires-Dist: setuptools>=77.0.3
Provides-Extra: dev
Requires-Dist: pre-commit>=4.2.0; extra == 'dev'
Requires-Dist: pytest-asyncio>=0.25.3; extra == 'dev'
Requires-Dist: pytest-cov>=6.0.0; extra == 'dev'
Requires-Dist: pytest>=8.3.5; extra == 'dev'
